coininfo_tanvi/__init__.py
coininfo_tanvi/info.py
coininfo_tanvi-1.1.dist-info/METADATA
coininfo_tanvi-1.1.dist-info/WHEEL
coininfo_tanvi-1.1.dist-info/top_level.txt
coininfo_tanvi-1.1.dist-info/RECORD
